docker_registry_py/__init__.py
docker_registry_py/container_registry.py
docker_registry_py-0.1.3.dist-info/LICENSE.txt
docker_registry_py-0.1.3.dist-info/METADATA
docker_registry_py-0.1.3.dist-info/WHEEL
docker_registry_py-0.1.3.dist-info/entry_points.txt
docker_registry_py-0.1.3.dist-info/RECORD
