Metadata-Version: 2.1
Name: docker-registry-py
Version: 0.1.3
Summary: A simple python program for managing container registry in private
Author: selva
Author-email: selva.g@subcom.tech
Requires-Python: >=3.10,<4.0
Classifier: Programming Language :: Python :: 3
Classifier: Programming Language :: Python :: 3.10
Classifier: Programming Language :: Python :: 3.11
Requires-Dist: docker (>=6.0.1,<7.0.0)
Requires-Dist: typer (>=0.7.0,<0.8.0)
